pcb_jigify/__init__.py
pcb_jigify/cli.py
pcb_jigify/jigs/__init__.py
pcb_jigify/jigs/base.py
pcb_jigify/jigs/holding.py
pcb_jigify/jigs/settings.py
pcb_jigify/jigs/testing.py
pcb_jigify-0.1.1.dist-info/METADATA
pcb_jigify-0.1.1.dist-info/WHEEL
pcb_jigify-0.1.1.dist-info/entry_points.txt
pcb_jigify-0.1.1.dist-info/RECORD
